{
  "company": "Great Elm Capital Corp",
  "table": "Schedule of Investments",
  "as_of": "2025-09-30",
  "currency": "USD",
  "records": [
    {
      "section": "Investments at Fair Value",
      "portfolio_company": "Advancion",
      "industry": "Chemicals",
      "security": "1st Lien, Secured Loan",
      "notes": "2, 16",
      "interest_rate": "1M SOFR + 4.00% (8.26%)",
      "initial_acquisition_date": "08/26/2025",
      "maturity": "11/24/2027",
      "par_amount_or_quantity": 3990,
      "cost": 3931,
      "fair_value": 3872,
      "percentage_of_class": null
    },
    {
      "section": "Investments at Fair Value",
      "portfolio_company": "Advancion",
      "industry": "Chemicals",
      "security": "2nd Lien, Secured Loan",
      "notes": "2, 16",
      "interest_rate": "1M SOFR + 7.75% (12.01%)",
      "initial_acquisition_date": "09/21/2022",
      "maturity": "11/24/2028",
      "par_amount_or_quantity": 1625,
      "cost": 1546,
      "fair_value": 1472,
      "percentage_of_class": null
    },
    {
      "section": "Investments at Fair Value",
      "portfolio_company": "American Coastal Insurance Corp.",
      "industry": "Insurance",
      "security": "Unsecured Bond",
      "notes": null,
      "interest_rate": 7.25,
      "initial_acquisition_date": "12/20/2022",
      "maturity": "12/15/2027",
      "par_amount_or_quantity": 13000,
      "cost": 9025,
      "fair_value": 13039,
      "percentage_of_class": null
    },
    {
      "section": "Investments at Fair Value",
      "portfolio_company": "Auction.com",
      "industry": "Financial Services",
      "security": "1st Lien, Secured Loan",
      "notes": "2, 6, 19",
      "interest_rate": "6M SOFR + 6.00% (10.04%)",
      "initial_acquisition_date": "09/09/2024",
      "maturity": "05/26/2028",
      "par_amount_or_quantity": 3164,
      "cost": 3046,
      "fair_value": 2893,
      "percentage_of_class": null
    },
    {
      "section": "Investments at Fair Value",
      "portfolio_company": "Avation Capital SA",
      "industry": "Aircraft",
      "security": "2nd Lien, Secured Bond",
      "notes": "10, 11",
      "interest_rate": 8.25,
      "initial_acquisition_date": "02/04/2022",
      "maturity": "10/31/2026",
      "par_amount_or_quantity": 4671,
      "cost": 4483,
      "fair_value": 4654,
      "percentage_of_class": null
    },
    {
      "section": "Investments at Fair Value",
      "portfolio_company": "Blackstone Secured Lending Fund",
      "industry": "Closed-End Fund",
      "security": "Common Equity",
      "notes": 10,
      "interest_rate": null,
      "initial_acquisition_date": "09/25/2024",
      "maturity": null,
      "par_amount_or_quantity": 6000,
      "cost": 182,
      "fair_value": 156,
      "percentage_of_class": "*"
    },
    {
      "section": "Investments at Fair Value",
      "portfolio_company": "Blue Ribbon, LLC",
      "industry": "Food & Staples",
      "security": "1st Lien, Secured Loan",
      "notes": "2, 6, 7, 16",
      "interest_rate": "3M SOFR + 8.00% (8.28% Cash + 4.00% PIK)",
      "initial_acquisition_date": "01/16/2025",
      "maturity": "05/08/2028",
      "par_amount_or_quantity": 249,
      "cost": 243,
      "fair_value": 245,
      "percentage_of_class": null
    },
    {
      "section": "Investments at Fair Value",
      "portfolio_company": "Brightline East, LLC",
      "industry": "Transportation",
      "security": "1st Lien, Secured Bond",
      "notes": 11,
      "interest_rate": 11.0,
      "initial_acquisition_date": "03/10/2025",
      "maturity": "01/31/2030",
      "par_amount_or_quantity": 925,
      "cost": 644,
      "fair_value": 380,
      "percentage_of_class": null
    },
    {
      "section": "Investments at Fair Value",
      "portfolio_company": "CLO Formation JV, LLC",
      "industry": "Structured Finance",
      "security": "Common Equity",
      "notes": "4, 10, 12",
      "interest_rate": null,
      "initial_acquisition_date": "04/23/2024",
      "maturity": null,
      "par_amount_or_quantity": 166,
      "cost": 52359,
      "fair_value": 45397,
      "percentage_of_class": 71.25
    },
    {
      "section": "Investments at Fair Value",
      "portfolio_company": "CMI Marketing, Inc.",
      "industry": "Marketing Services",
      "security": "1st Lien, Secured Loan",
      "notes": "2, 6, 15",
      "interest_rate": "1M SOFR + 4.25% (8.53%)",
      "initial_acquisition_date": "09/05/2025",
      "maturity": "03/23/2028",
      "par_amount_or_quantity": 1895,
      "cost": 1881,
      "fair_value": 1881,
      "percentage_of_class": null
    },
    {
      "section": "Investments at Fair Value",
      "portfolio_company": "Commercial Vehicle Group, Inc.",
      "industry": "Transportation Equipment Manufacturing",
      "security": "1st Lien, Secured Loan",
      "notes": "2, 6, 20",
      "interest_rate": "1M SOFR + 9.75% (14.01%)",
      "initial_acquisition_date": "07/31/2025",
      "maturity": "06/27/2030",
      "par_amount_or_quantity": 4988,
      "cost": 4841,
      "fair_value": 4838,
      "percentage_of_class": null
    },
    {
      "section": "Investments at Fair Value",
      "portfolio_company": "Commercial Vehicle Group, Inc.",
      "industry": "Transportation Equipment Manufacturing",
      "security": "Tranche 1 warrants",
      "notes": "6, 8, 23",
      "interest_rate": null,
      "initial_acquisition_date": "07/31/2025",
      "maturity": "06/25/2030",
      "par_amount_or_quantity": 103547,
      "cost": null,
      "fair_value": 98,
      "percentage_of_class": null
    },
    {
      "section": "Investments at Fair Value",
      "portfolio_company": "Commercial Vehicle Group, Inc.",
      "industry": "Transportation Equipment Manufacturing",
      "security": "Tranche 2 warrants",
      "notes": "6, 8, 23",
      "interest_rate": null,
      "initial_acquisition_date": "07/31/2025",
      "maturity": "06/25/2030",
      "par_amount_or_quantity": 103547,
      "cost": null,
      "fair_value": 86,
      "percentage_of_class": null
    },
    {
      "section": "Investments at Fair Value",
      "portfolio_company": "Confluence Technologies",
      "industry": "Technology",
      "security": "1st Lien, Secured Loan",
      "notes": "2, 15",
      "interest_rate": "3M SOFR + 3.75% (7.90%)",
      "initial_acquisition_date": "03/04/2025",
      "maturity": "07/31/2028",
      "par_amount_or_quantity": 1098,
      "cost": 994,
      "fair_value": 901,
      "percentage_of_class": null
    },
    {
      "section": "Investments at Fair Value",
      "portfolio_company": "Conuma Resources LTD",
      "industry": "Metals & Mining",
      "security": "1st Lien, Secured Bond",
      "notes": "6, 10, 11",
      "interest_rate": 13.13,
      "initial_acquisition_date": "08/08/2024",
      "maturity": "05/01/2028",
      "par_amount_or_quantity": 4055,
      "cost": 4131,
      "fair_value": 3614,
      "percentage_of_class": null
    },
    {
      "section": "Investments at Fair Value",
      "portfolio_company": "Conuma Resources LTD",
      "industry": "Metals & Mining",
      "security": "1st Lien, Secured Bond",
      "notes": "6, 10, 11",
      "interest_rate": 13.13,
      "initial_acquisition_date": "04/15/2025",
      "maturity": "05/01/2028",
      "par_amount_or_quantity": 1400,
      "cost": 1369,
      "fair_value": 1381,
      "percentage_of_class": null
    },
    {
      "section": "Investments at Fair Value",
      "portfolio_company": "Coreweave Compute Acquisition Co. II, LLC",
      "industry": "Technology",
      "security": "1st Lien, Secured Loan",
      "notes": "2, 6, 14",
      "interest_rate": "3M SOFR + 9.62% (13.77%)",
      "initial_acquisition_date": "08/21/2023",
      "maturity": "07/31/2028",
      "par_amount_or_quantity": 12688,
      "cost": 12636,
      "fair_value": 13005,
      "percentage_of_class": null
    },
    {
      "section": "Investments at Fair Value",
      "portfolio_company": "Coreweave Compute Acquisition Co. IV, LLC",
      "industry": "Technology",
      "security": "1st Lien, Secured Loan",
      "notes": "2, 6, 14",
      "interest_rate": "3M SOFR + 6.00% (10.23%)",
      "initial_acquisition_date": "05/29/2024",
      "maturity": "05/16/2030",
      "par_amount_or_quantity": 3314,
      "cost": 3271,
      "fair_value": 3380,
      "percentage_of_class": null
    },
    {
      "section": "Investments at Fair Value",
      "portfolio_company": "CSC ServiceWorks",
      "industry": "Consumer Services",
      "security": "1st Lien, Secured Loan",
      "notes": "2, 16",
      "interest_rate": "3M SOFR + 4.00% (8.39%)",
      "initial_acquisition_date": "09/26/2023",
      "maturity": "03/04/2028",
      "par_amount_or_quantity": 4006,
      "cost": 3551,
      "fair_value": 3340,
      "percentage_of_class": null
    },
    {
      "section": "Investments at Fair Value",
      "portfolio_company": "CW Opportunity 2 LP",
      "industry": "Technology",
      "security": "Private Fund",
      "notes": "10, 12",
      "interest_rate": null,
      "initial_acquisition_date": "05/14/2024",
      "maturity": null,
      "par_amount_or_quantity": 5002186,
      "cost": 5002,
      "fair_value": 14756,
      "percentage_of_class": null
    },
    {
      "section": "Investments at Fair Value",
      "portfolio_company": "Del Monte Foods Corp II Inc",
      "industry": "Food & Staples",
      "security": "Jr. DIP Loan",
      "notes": "2, 6, 7, 17",
      "interest_rate": "1M SOFR + 9.50% (0.00% Cash + 13.77% PIK)",
      "initial_acquisition_date": "07/14/2025",
      "maturity": "04/02/2026",
      "par_amount_or_quantity": 3945,
      "cost": 3942,
      "fair_value": 3945,
      "percentage_of_class": null
    },
    {
      "section": "Investments at Fair Value",
      "portfolio_company": "Del Monte Foods Corp II Inc",
      "industry": "Food & Staples",
      "security": "Sr. DIP Loan",
      "notes": "2, 6, 7, 17",
      "interest_rate": "1M SOFR + 9.50% (5.27% Cash + 8.50% PIK)",
      "initial_acquisition_date": "07/14/2025",
      "maturity": "04/02/2026",
      "par_amount_or_quantity": 2709,
      "cost": 2631,
      "fair_value": 2709,
      "percentage_of_class": null
    },
    {
      "section": "Investments at Fair Value",
      "portfolio_company": "Del Monte Foods Corp II Inc",
      "industry": "Food & Staples",
      "security": "1st Lien, Secured Loan",
      "notes": "2, 6, 8, 9",
      "interest_rate": null,
      "initial_acquisition_date": "10/16/2024",
      "maturity": "08/02/2028",
      "par_amount_or_quantity": 2040,
      "cost": 2035,
      "fair_value": 1051,
      "percentage_of_class": null
    },
    {
      "section": "Investments at Fair Value",
      "portfolio_company": "Del Monte Foods Corp II Inc",
      "industry": "Food & Staples",
      "security": "1st Lien, Secured Loan",
      "notes": "2, 6, 8, 9",
      "interest_rate": null,
      "initial_acquisition_date": "04/17/2025",
      "maturity": "08/02/2028",
      "par_amount_or_quantity": 264,
      "cost": 258,
      "fair_value": 136,
      "percentage_of_class": null
    },
    {
      "section": "Investments at Fair Value",
      "portfolio_company": "DTI Holdco, Inc.",
      "industry": "Business Services",
      "security": "1st Lien, Secured Loan",
      "notes": "2, 16",
      "interest_rate": "1M SOFR + 4.00% (8.16%)",
      "initial_acquisition_date": "09/04/2025",
      "maturity": "04/26/2029",
      "par_amount_or_quantity": 1895,
      "cost": 1774,
      "fair_value": 1681,
      "percentage_of_class": null
    },
    {
      "section": "Investments at Fair Value",
      "portfolio_company": "Dynata, LLC (New Insight Holdings, Inc.)",
      "industry": "Internet Media",
      "security": "1st Lien, Secured Loan",
      "notes": "2, 17",
      "interest_rate": "3M SOFR + 5.50% (9.96%)",
      "initial_acquisition_date": "07/15/2024",
      "maturity": "10/15/2028",
      "par_amount_or_quantity": 4732,
      "cost": 4732,
      "fair_value": 3853,
      "percentage_of_class": null
    },
    {
      "section": "Investments at Fair Value",
      "portfolio_company": "Dynata, LLC (New Insight Holdings, Inc.)",
      "industry": "Internet Media",
      "security": "Common Equity",
      "notes": "6, 8",
      "interest_rate": null,
      "initial_acquisition_date": "07/15/2024",
      "maturity": null,
      "par_amount_or_quantity": 100000,
      "cost": 11231,
      "fair_value": 1611,
      "percentage_of_class": 1.0
    },
    {
      "section": "Investments at Fair Value",
      "portfolio_company": "Dynata, LLC (New Insight Holdings, Inc.)",
      "industry": "Internet Media",
      "security": "Warrants",
      "notes": "6, 8, 23",
      "interest_rate": null,
      "initial_acquisition_date": "07/15/2024",
      "maturity": "07/15/2029",
      "par_amount_or_quantity": 45714,
      "cost": null,
      "fair_value": null,
      "percentage_of_class": 3.2
    },
    {
      "section": "Investments at Fair Value",
      "portfolio_company": "EagleView Technology Corp",
      "industry": "Technology",
      "security": "1st Lien, Secured Loan",
      "notes": "2, 7, 20",
      "interest_rate": "3M SOFR + 6.50% (9.50% Cash + 1.00% PIK)",
      "initial_acquisition_date": "03/27/2025",
      "maturity": "08/14/2028",
      "par_amount_or_quantity": 6216,
      "cost": 6065,
      "fair_value": 6095,
      "percentage_of_class": null
    },
    {
      "section": "Investments at Fair Value",
      "portfolio_company": "Elevate Textiles, Inc.",
      "industry": "Textiles",
      "security": "1st Lien, Secured Loan",
      "notes": "2, 6, 7, 17",
      "interest_rate": "3M SOFR + 6.50% (5.44% Cash + 5.50% PIK)",
      "initial_acquisition_date": "11/07/2024",
      "maturity": "09/30/2027",
      "par_amount_or_quantity": 2533,
      "cost": 2118,
      "fair_value": 2108,
      "percentage_of_class": null
    },
    {
      "section": "Investments at Fair Value",
      "portfolio_company": "First Brands, Inc.",
      "industry": "Transportation Equipment Manufacturing",
      "security": "1st Lien, Secured Loan",
      "notes": "2, 8, 9",
      "interest_rate": null,
      "initial_acquisition_date": "06/09/2023",
      "maturity": "03/30/2027",
      "par_amount_or_quantity": 4797,
      "cost": 4774,
      "fair_value": 1688,
      "percentage_of_class": null
    },
    {
      "section": "Investments at Fair Value",
      "portfolio_company": "First Brands, Inc.",
      "industry": "Transportation Equipment Manufacturing",
      "security": "2nd Lien, Secured Loan",
      "notes": "2, 8, 9",
      "interest_rate": null,
      "initial_acquisition_date": "03/24/2021",
      "maturity": "03/30/2028",
      "par_amount_or_quantity": 16200,
      "cost": 15807,
      "fair_value": 898,
      "percentage_of_class": null
    },
    {
      "section": "Investments at Fair Value",
      "portfolio_company": "Flexsys Cayman Holdings, LP",
      "industry": "Chemicals",
      "security": "1st Lien, Secured Loan",
      "notes": "2, 16",
      "interest_rate": "3M SOFR + 6.25% (10.45%)",
      "initial_acquisition_date": "05/23/2025",
      "maturity": "08/01/2029",
      "par_amount_or_quantity": 1820,
      "cost": 1786,
      "fair_value": 1548,
      "percentage_of_class": null
    },
    {
      "section": "Investments at Fair Value",
      "portfolio_company": "Flexsys Cayman Holdings, LP",
      "industry": "Chemicals",
      "security": "1st Lien, Secured Loan",
      "notes": "2, 16",
      "interest_rate": "3M SOFR + 5.25% (9.71%)",
      "initial_acquisition_date": "05/28/2025",
      "maturity": "08/01/2029",
      "par_amount_or_quantity": 5992,
      "cost": 5082,
      "fair_value": 1940,
      "percentage_of_class": null
    },
    {
      "section": "Investments at Fair Value",
      "portfolio_company": "Foresight Energy",
      "industry": "Metals & Mining",
      "security": "1st Lien, Secured Loan",
      "notes": "2, 6, 19",
      "interest_rate": "3M SOFR + 8.00% (12.10%)",
      "initial_acquisition_date": "07/29/2021",
      "maturity": "06/30/2027",
      "par_amount_or_quantity": 5840,
      "cost": 5856,
      "fair_value": 5565,
      "percentage_of_class": null
    },
    {
      "section": "Investments at Fair Value",
      "portfolio_company": "Form Technologies LLC",
      "industry": "Industrial",
      "security": "1st Lien, Secured Loan",
      "notes": "2, 15",
      "interest_rate": "3M SOFR + 5.75% (10.08%)",
      "initial_acquisition_date": "11/01/2024",
      "maturity": "07/19/2030",
      "par_amount_or_quantity": 4738,
      "cost": 4653,
      "fair_value": 4150,
      "percentage_of_class": null
    },
    {
      "section": "Investments at Fair Value",
      "portfolio_company": "FPL Food LLC",
      "industry": "Food & Staples",
      "security": "1st Lien, Secured Loan",
      "notes": "2, 6, 14, 22",
      "interest_rate": "PRIME + 3.25% (11.50%)",
      "initial_acquisition_date": "10/02/2024",
      "maturity": "02/13/2027",
      "par_amount_or_quantity": 4000,
      "cost": 4000,
      "fair_value": 4020,
      "percentage_of_class": null
    },
    {
      "section": "Investments at Fair Value",
      "portfolio_company": "FS KKR CAPITAL CORP",
      "industry": "Closed-End Fund",
      "security": "Common Equity",
      "notes": 10,
      "interest_rate": null,
      "initial_acquisition_date": "05/09/2024",
      "maturity": null,
      "par_amount_or_quantity": 250000,
      "cost": 4445,
      "fair_value": 3733,
      "percentage_of_class": "*"
    },
    {
      "section": "Investments at Fair Value",
      "portfolio_company": "Globoforce Limited",
      "industry": "Commercial Services",
      "security": "Factoring Participation",
      "notes": "6, 10",
      "interest_rate": 0.0,
      "initial_acquisition_date": "09/25/2025",
      "maturity": "06/24/2026",
      "par_amount_or_quantity": 6000,
      "cost": 6000,
      "fair_value": 6000,
      "percentage_of_class": null
    },
    {
      "section": "Investments at Fair Value",
      "portfolio_company": "Graftech",
      "industry": "Industrial",
      "security": "2nd Lien, Secured Bond",
      "notes": 11,
      "interest_rate": 9.88,
      "initial_acquisition_date": "04/25/2025",
      "maturity": "12/23/2029",
      "par_amount_or_quantity": 1470,
      "cost": 1123,
      "fair_value": 1255,
      "percentage_of_class": null
    },
    {
      "section": "Investments at Fair Value",
      "portfolio_company": "Great Elm Specialty Finance, LLC",
      "industry": "Specialty Finance",
      "security": "Common Equity",
      "notes": "4, 6",
      "interest_rate": null,
      "initial_acquisition_date": "09/01/2023",
      "maturity": null,
      "par_amount_or_quantity": 87500,
      "cost": 17000,
      "fair_value": 13370,
      "percentage_of_class": 87.5
    },
    {
      "section": "Investments at Fair Value",
      "portfolio_company": "Great Elm Specialty Finance, LLC",
      "industry": "Specialty Finance",
      "security": "Subordinated Note",
      "notes": "4, 6",
      "interest_rate": 13.0,
      "initial_acquisition_date": "09/01/2023",
      "maturity": "06/30/2026",
      "par_amount_or_quantity": 25325,
      "cost": 25325,
      "fair_value": 25325,
      "percentage_of_class": null
    },
    {
      "section": "Investments at Fair Value",
      "portfolio_company": "Greenfire Resources Ltd.",
      "industry": "Oil & Gas Exploration & Production",
      "security": "1st Lien, Secured Bond",
      "notes": "10, 11",
      "interest_rate": 12.0,
      "initial_acquisition_date": "09/13/2023",
      "maturity": "10/01/2028",
      "par_amount_or_quantity": 4152,
      "cost": 4096,
      "fair_value": 4399,
      "percentage_of_class": null
    },
    {
      "section": "Investments at Fair Value",
      "portfolio_company": "Inmar Inc.",
      "industry": "Consumer Services",
      "security": "1st Lien, Secured Loan",
      "notes": "2, 14",
      "interest_rate": "1M SOFR + 4.50% (8.66%)",
      "initial_acquisition_date": "10/31/2024",
      "maturity": "10/30/2031",
      "par_amount_or_quantity": 7187,
      "cost": 7174,
      "fair_value": 7156,
      "percentage_of_class": null
    },
    {
      "section": "Investments at Fair Value",
      "portfolio_company": "Ipsen US Holdings, Inc.",
      "industry": "Industrial",
      "security": "1st Lien, Secured Loan",
      "notes": "2, 6, 7, 21",
      "interest_rate": "1M SOFR + 12.09% (7.45% Cash + 8.81% PIK)",
      "initial_acquisition_date": "08/14/2024",
      "maturity": "07/31/2029",
      "par_amount_or_quantity": 5469,
      "cost": 5315,
      "fair_value": 5186,
      "percentage_of_class": null
    },
    {
      "section": "Investments at Fair Value",
      "portfolio_company": "Mad Engine Global, LLC",
      "industry": "Apparel",
      "security": "1st Lien, Secured Loan",
      "notes": "2, 6, 17",
      "interest_rate": "3M SOFR + 7.00% (11.26%)",
      "initial_acquisition_date": "06/30/2021",
      "maturity": "07/15/2027",
      "par_amount_or_quantity": 6487,
      "cost": 5965,
      "fair_value": 5699,
      "percentage_of_class": null
    },
    {
      "section": "Investments at Fair Value",
      "portfolio_company": "Main Street Sports Group LLC",
      "industry": "Media",
      "security": "1st Lien, Secured Loan",
      "notes": 7,
      "interest_rate": 15.0,
      "initial_acquisition_date": "02/06/2025",
      "maturity": "01/03/2028",
      "par_amount_or_quantity": 112,
      "cost": 105,
      "fair_value": 95,
      "percentage_of_class": null
    },
    {
      "section": "Investments at Fair Value",
      "portfolio_company": "Manchester Acquisition Sub, LLC",
      "industry": "Chemicals",
      "security": "1st Lien, Secured Loan",
      "notes": "2, 6, 16",
      "interest_rate": "3M SOFR + 5.75% (10.07%)",
      "initial_acquisition_date": "09/26/2023",
      "maturity": "12/01/2026",
      "par_amount_or_quantity": 7487,
      "cost": 7223,
      "fair_value": 7178,
      "percentage_of_class": null
    },
    {
      "section": "Investments at Fair Value",
      "portfolio_company": "Maverick Gaming LLC",
      "industry": "Casinos & Gaming",
      "security": "Jr. DIP Loan",
      "notes": "2, 6, 7, 20",
      "interest_rate": "1M SOFR + 12.50% (5.16% Cash + 11.50% PIK)",
      "initial_acquisition_date": "07/16/2025",
      "maturity": "04/16/2026",
      "par_amount_or_quantity": 1557,
      "cost": 1503,
      "fair_value": 1556,
      "percentage_of_class": null
    },
    {
      "section": "Investments at Fair Value",
      "portfolio_company": "Maverick Gaming LLC",
      "industry": "Casinos & Gaming",
      "security": "Sr. DIP Loan",
      "notes": "2, 6, 20",
      "interest_rate": "1M SOFR + 12.50% (16.66%)",
      "initial_acquisition_date": "07/31/2025",
      "maturity": "04/16/2026",
      "par_amount_or_quantity": 907,
      "cost": 876,
      "fair_value": 907,
      "percentage_of_class": null
    },
    {
      "section": "Investments at Fair Value",
      "portfolio_company": "Maverick Gaming LLC",
      "industry": "Casinos & Gaming",
      "security": "1st Lien, Secured Loan",
      "notes": "2, 6, 8, 9",
      "interest_rate": null,
      "initial_acquisition_date": "04/03/2024",
      "maturity": "06/03/2028",
      "par_amount_or_quantity": 5741,
      "cost": 6353,
      "fair_value": 1086,
      "percentage_of_class": null
    },
    {
      "section": "Investments at Fair Value",
      "portfolio_company": "New Wilkie Energy Pty Limited",
      "industry": "Metals & Mining",
      "security": "1st Lien, Secured Loan",
      "notes": "6, 8, 10",
      "interest_rate": null,
      "initial_acquisition_date": "02/20/2025",
      "maturity": "02/20/2027",
      "par_amount_or_quantity": 1268,
      "cost": 1235,
      "fair_value": 1268,
      "percentage_of_class": null
    },
    {
      "section": "Investments at Fair Value",
      "portfolio_company": "New Wilkie Energy Pty Limited",
      "industry": "Metals & Mining",
      "security": "1st Lien, Secured Loan",
      "notes": "6, 8, 10",
      "interest_rate": null,
      "initial_acquisition_date": "02/20/2025",
      "maturity": "02/20/2027",
      "par_amount_or_quantity": 114,
      "cost": 111,
      "fair_value": 114,
      "percentage_of_class": null
    },
    {
      "section": "Investments at Fair Value",
      "portfolio_company": "New Wilkie Energy Pty Limited",
      "industry": "Metals & Mining",
      "security": "2nd Lien, Secured Loan",
      "notes": "6, 8, 10",
      "interest_rate": null,
      "initial_acquisition_date": "02/20/2025",
      "maturity": "02/20/2099",
      "par_amount_or_quantity": 4153,
      "cost": 4973,
      "fair_value": 1246,
      "percentage_of_class": null
    },
    {
      "section": "Investments at Fair Value",
      "portfolio_company": "NGC CLO 2 Ltd.",
      "industry": "Structured Finance",
      "security": "CLO Equity",
      "notes": "6, 10",
      "interest_rate": 16.6,
      "initial_acquisition_date": "03/07/2025",
      "maturity": "04/20/2038",
      "par_amount_or_quantity": 7410,
      "cost": 6190,
      "fair_value": 6907,
      "percentage_of_class": null
    },
    {
      "section": "Investments at Fair Value",
      "portfolio_company": "Northeast Grocery Inc",
      "industry": "Food & Staples",
      "security": "1st Lien, Secured Loan",
      "notes": "2, 6, 17",
      "interest_rate": "3M SOFR + 7.50% (11.69%)",
      "initial_acquisition_date": "08/08/2024",
      "maturity": "12/13/2028",
      "par_amount_or_quantity": 2516,
      "cost": 2541,
      "fair_value": 2535,
      "percentage_of_class": null
    },
    {
      "section": "Investments at Fair Value",
      "portfolio_company": "PFS Holdings Corp.",
      "industry": "Food & Staples",
      "security": "Common Equity",
      "notes": "5, 6, 8",
      "interest_rate": null,
      "initial_acquisition_date": "11/13/2020",
      "maturity": null,
      "par_amount_or_quantity": 5238,
      "cost": 12379,
      "fair_value": null,
      "percentage_of_class": 5.05
    },
    {
      "section": "Investments at Fair Value",
      "portfolio_company": "PowerStop LLC",
      "industry": "Transportation Equipment Manufacturing",
      "security": "1st Lien, Secured Loan",
      "notes": "2, 15",
      "interest_rate": "3M SOFR + 4.75% (9.16%)",
      "initial_acquisition_date": "02/09/2024",
      "maturity": "01/26/2029",
      "par_amount_or_quantity": 1603,
      "cost": 1499,
      "fair_value": 1295,
      "percentage_of_class": null
    },
    {
      "section": "Investments at Fair Value",
      "portfolio_company": "ProFrac Holdings II, LLC",
      "industry": "Energy Services",
      "security": "1st Lien, Secured Bond",
      "notes": "2, 6, 10, 11, 21",
      "interest_rate": "3M SOFR + 7.25% (11.81%)",
      "initial_acquisition_date": "12/27/2023",
      "maturity": "01/23/2029",
      "par_amount_or_quantity": 5762,
      "cost": 5720,
      "fair_value": 5690,
      "percentage_of_class": null
    },
    {
      "section": "Investments at Fair Value",
      "portfolio_company": "Quirch Foods, Co.",
      "industry": "Food & Staples",
      "security": "1st Lien, Secured Loan",
      "notes": "2, 17",
      "interest_rate": "1M SOFR + 4.75% (9.05%)",
      "initial_acquisition_date": "08/25/2025",
      "maturity": "10/27/2027",
      "par_amount_or_quantity": 1995,
      "cost": 1965,
      "fair_value": 1953,
      "percentage_of_class": null
    },
    {
      "section": "Investments at Fair Value",
      "portfolio_company": "Ruby Tuesday Operations LLC",
      "industry": "Restaurants",
      "security": "1st Lien, Secured Loan",
      "notes": "2, 6, 7, 18",
      "interest_rate": "1M SOFR + 16.00% (0.00% Cash + 20.39% PIK)",
      "initial_acquisition_date": "01/31/2023",
      "maturity": "02/24/2027",
      "par_amount_or_quantity": 160,
      "cost": 160,
      "fair_value": 159,
      "percentage_of_class": null
    },
    {
      "section": "Investments at Fair Value",
      "portfolio_company": "Ruby Tuesday Operations LLC",
      "industry": "Restaurants",
      "security": "1st Lien, Secured Loan",
      "notes": "2, 6, 7, 18",
      "interest_rate": "1M SOFR + 12.00% (10.39% Cash + 6.00% PIK)",
      "initial_acquisition_date": "09/03/2024",
      "maturity": "02/24/2027",
      "par_amount_or_quantity": 2651,
      "cost": 2635,
      "fair_value": 2593,
      "percentage_of_class": null
    },
    {
      "section": "Investments at Fair Value",
      "portfolio_company": "Ruby Tuesday Operations LLC",
      "industry": "Restaurants",
      "security": "Warrants",
      "notes": "6, 8, 23",
      "interest_rate": null,
      "initial_acquisition_date": "02/24/2021",
      "maturity": "02/24/2027",
      "par_amount_or_quantity": 311697,
      "cost": null,
      "fair_value": 312,
      "percentage_of_class": 2.81
    },
    {
      "section": "Investments at Fair Value",
      "portfolio_company": "SIRVA Worldwide Inc",
      "industry": "Business Services",
      "security": "1st Lien, Secured Loan",
      "notes": "2, 6, 20",
      "interest_rate": "3M SOFR + 8.00% (12.00%)",
      "initial_acquisition_date": "02/06/2025",
      "maturity": "02/20/2029",
      "par_amount_or_quantity": 700,
      "cost": 693,
      "fair_value": 651,
      "percentage_of_class": null
    },
    {
      "section": "Investments at Fair Value",
      "portfolio_company": "SIRVA Worldwide Inc",
      "industry": "Business Services",
      "security": "Delayed Draw, Secured Loan",
      "notes": "2, 6, 20",
      "interest_rate": "3M SOFR + 8.00% (12.00%)",
      "initial_acquisition_date": "02/19/2025",
      "maturity": "02/20/2029",
      "par_amount_or_quantity": 80,
      "cost": 79,
      "fair_value": 71,
      "percentage_of_class": null
    },
    {
      "section": "Investments at Fair Value",
      "portfolio_company": "Stone Ridge Opportunities Fund L.P.",
      "industry": "Insurance",
      "security": "Private Fund",
      "notes": "8, 10, 12",
      "interest_rate": null,
      "initial_acquisition_date": "01/01/2023",
      "maturity": null,
      "par_amount_or_quantity": 2379875,
      "cost": 2389,
      "fair_value": 4451,
      "percentage_of_class": null
    },
    {
      "section": "Investments at Fair Value",
      "portfolio_company": "Thryv, Inc.",
      "industry": "Marketing Services",
      "security": "1st Lien, Secured Loan",
      "notes": "2, 6, 10, 17",
      "interest_rate": "1M SOFR + 6.75% (10.91%)",
      "initial_acquisition_date": "04/30/2024",
      "maturity": "05/01/2029",
      "par_amount_or_quantity": 1215,
      "cost": 1206,
      "fair_value": 1202,
      "percentage_of_class": null
    },
    {
      "section": "Investments at Fair Value",
      "portfolio_company": "TPC Group Inc",
      "industry": "Chemicals",
      "security": "1st Lien, Secured Loan",
      "notes": "2, 14",
      "interest_rate": "6M SOFR + 5.75% (9.77%)",
      "initial_acquisition_date": "11/22/2024",
      "maturity": "12/16/2031",
      "par_amount_or_quantity": 945,
      "cost": 932,
      "fair_value": 915,
      "percentage_of_class": null
    },
    {
      "section": "Investments at Fair Value",
      "portfolio_company": "Trouvaille Re Ltd.",
      "industry": "Insurance",
      "security": "Preference Shares",
      "notes": "6, 10",
      "interest_rate": null,
      "initial_acquisition_date": "03/27/2024",
      "maturity": null,
      "par_amount_or_quantity": 100,
      "cost": 5000,
      "fair_value": 6629,
      "percentage_of_class": null
    },
    {
      "section": "Investments at Fair Value",
      "portfolio_company": "TRU Taj Trust",
      "industry": "Retail",
      "security": "Common Equity",
      "notes": "6, 8",
      "interest_rate": null,
      "initial_acquisition_date": "07/21/2017",
      "maturity": null,
      "par_amount_or_quantity": 16000,
      "cost": 611,
      "fair_value": 85,
      "percentage_of_class": 2.75
    },
    {
      "section": "Investments at Fair Value",
      "portfolio_company": "TruGreen LP",
      "industry": "Consumer Services",
      "security": "1st Lien, Secured Loan",
      "notes": "2, 16",
      "interest_rate": "1M SOFR + 4.00% (8.26%)",
      "initial_acquisition_date": "05/14/2024",
      "maturity": "11/02/2027",
      "par_amount_or_quantity": 1772,
      "cost": 1718,
      "fair_value": 1737,
      "percentage_of_class": null
    },
    {
      "section": "Investments at Fair Value",
      "portfolio_company": "TruGreen LP",
      "industry": "Consumer Services",
      "security": "2nd Lien, Secured Loan",
      "notes": "2, 16",
      "interest_rate": "3M SOFR + 8.50% (13.07%)",
      "initial_acquisition_date": "05/14/2024",
      "maturity": "11/02/2028",
      "par_amount_or_quantity": 900,
      "cost": 739,
      "fair_value": 793,
      "percentage_of_class": null
    },
    {
      "section": "Investments at Fair Value",
      "portfolio_company": "Universal Fiber Systems",
      "industry": "Chemicals",
      "security": "1st Lien, Secured Loan",
      "notes": "2, 6, 7, 17",
      "interest_rate": "1M SOFR + 12.00% (8.28% Cash + 8.00% PIK)",
      "initial_acquisition_date": "10/16/2024",
      "maturity": "09/30/2028",
      "par_amount_or_quantity": 5791,
      "cost": 5784,
      "fair_value": 5743,
      "percentage_of_class": null
    },
    {
      "section": "Investments at Fair Value",
      "portfolio_company": "Universal Fiber Systems",
      "industry": "Chemicals",
      "security": "Common Equity",
      "notes": "6, 8",
      "interest_rate": null,
      "initial_acquisition_date": "10/16/2024",
      "maturity": null,
      "par_amount_or_quantity": 41687,
      "cost": 6809,
      "fair_value": 6079,
      "percentage_of_class": 5.44
    },
    {
      "section": "Investments at Fair Value",
      "portfolio_company": "Universal Fiber Systems",
      "industry": "Chemicals",
      "security": "Common Equity",
      "notes": "6, 8",
      "interest_rate": null,
      "initial_acquisition_date": "10/16/2024",
      "maturity": null,
      "par_amount_or_quantity": 371,
      "cost": null,
      "fair_value": null,
      "percentage_of_class": "*"
    },
    {
      "section": "Investments at Fair Value",
      "portfolio_company": "Universal Fiber Systems",
      "industry": "Chemicals",
      "security": "Common Equity",
      "notes": "6, 8",
      "interest_rate": null,
      "initial_acquisition_date": "10/16/2024",
      "maturity": null,
      "par_amount_or_quantity": 976,
      "cost": null,
      "fair_value": null,
      "percentage_of_class": 2.37
    },
    {
      "section": "Investments at Fair Value",
      "portfolio_company": "Victra Holdings, LLC",
      "industry": "Retail",
      "security": "1st Lien, Secured Loan",
      "notes": "2, 16",
      "interest_rate": "3M SOFR + 3.75% (7.75%)",
      "initial_acquisition_date": "09/10/2024",
      "maturity": "03/31/2029",
      "par_amount_or_quantity": 1383,
      "cost": 1383,
      "fair_value": 1383,
      "percentage_of_class": null
    },
    {
      "section": "Investments at Fair Value",
      "portfolio_company": "Vivos Holdings, LLC",
      "industry": "Consumer Products",
      "security": "1st Lien, Secured Loan",
      "notes": "2, 6, 19",
      "interest_rate": "1M SOFR + 6.00% (10.15%)",
      "initial_acquisition_date": "08/13/2025",
      "maturity": "08/13/2030",
      "par_amount_or_quantity": 4750,
      "cost": 4703,
      "fair_value": 4710,
      "percentage_of_class": null
    },
    {
      "section": "Investments at Fair Value",
      "portfolio_company": "Vivos Holdings, LLC",
      "industry": "Consumer Products",
      "security": "2nd Lien, Secured Loan",
      "notes": "2, 6, 7, 21",
      "interest_rate": "1M SOFR + 10.00% (0.00% Cash + 14.16% PIK)",
      "initial_acquisition_date": "08/13/2025",
      "maturity": "02/13/2031",
      "par_amount_or_quantity": 9667,
      "cost": 9667,
      "fair_value": 9689,
      "percentage_of_class": null
    },
    {
      "section": "Investments at Fair Value",
      "portfolio_company": "Vivos Holdings, LLC",
      "industry": "Consumer Products",
      "security": "Promissory Note",
      "notes": "6, 7",
      "interest_rate": 4.5,
      "initial_acquisition_date": "08/13/2025",
      "maturity": "08/13/2032",
      "par_amount_or_quantity": 2045,
      "cost": 2045,
      "fair_value": 2045,
      "percentage_of_class": null
    },
    {
      "section": "Investments at Fair Value",
      "portfolio_company": "Vivos Holdings, LLC",
      "industry": "Consumer Products",
      "security": "Promissory Note",
      "notes": "6, 7",
      "interest_rate": "9.00% (0.00% Cash + 9.00% PIK)",
      "initial_acquisition_date": "08/13/2025",
      "maturity": "08/13/2032",
      "par_amount_or_quantity": 131,
      "cost": 131,
      "fair_value": 131,
      "percentage_of_class": null
    },
    {
      "section": "Investments at Fair Value",
      "portfolio_company": "Vivos Holdings, LLC",
      "industry": "Consumer Products",
      "security": "Warrants",
      "notes": "6, 8, 23",
      "interest_rate": null,
      "initial_acquisition_date": "08/13/2025",
      "maturity": "08/13/2031",
      "par_amount_or_quantity": 592,
      "cost": null,
      "fair_value": 769,
      "percentage_of_class": "*"
    },
    {
      "section": "Investments at Fair Value",
      "portfolio_company": "Walor North America, Inc",
      "industry": "Industrial",
      "security": "1st Lien, Secured Loan",
      "notes": "2, 6, 14",
      "interest_rate": "1M SOFR + 5.75% (10.03%)",
      "initial_acquisition_date": "06/17/2025",
      "maturity": "06/17/2028",
      "par_amount_or_quantity": 1500,
      "cost": 1500,
      "fair_value": 1500,
      "percentage_of_class": null
    },
    {
      "section": "Investments at Fair Value",
      "portfolio_company": "W&T Offshore, Inc.",
      "industry": "Oil & Gas Exploration & Production",
      "security": "2nd Lien, Secured Bond",
      "notes": null,
      "interest_rate": 10.75,
      "initial_acquisition_date": "01/14/2025",
      "maturity": "02/02/2029",
      "par_amount_or_quantity": 6450,
      "cost": 6146,
      "fair_value": 6175,
      "percentage_of_class": null
    },
    {
      "section": "Investments at Fair Value",
      "portfolio_company": "x.AI LLC",
      "industry": "Technology",
      "security": "1st Lien, Secured Bond",
      "notes": null,
      "interest_rate": 12.5,
      "initial_acquisition_date": "08/29/2025",
      "maturity": "06/30/2030",
      "par_amount_or_quantity": 900,
      "cost": 898,
      "fair_value": 945,
      "percentage_of_class": null
    },
    {
      "section": "Investments at Fair Value",
      "portfolio_company": "Total Investments excluding Short-Term Investments (232.06% of Net Assets)",
      "industry": "Total Investments excluding Short-Term Investments (232.06% of Net Assets)",
      "security": "Total Investments excluding Short-Term Investments (232.06% of Net Assets)",
      "notes": "Total Investments excluding Short-Term Investments (232.06% of Net Assets)",
      "interest_rate": "Total Investments excluding Short-Term Investments (232.06% of Net Assets)",
      "initial_acquisition_date": null,
      "maturity": null,
      "par_amount_or_quantity": null,
      "cost": 374223,
      "fair_value": 325106,
      "percentage_of_class": null
    },
    {
      "section": "Investments at Fair Value",
      "portfolio_company": "Short-Term Investments",
      "industry": "Short-Term Investments",
      "security": "Short-Term Investments",
      "notes": "Short-Term Investments",
      "interest_rate": null,
      "initial_acquisition_date": null,
      "maturity": null,
      "par_amount_or_quantity": null,
      "cost": null,
      "fair_value": null,
      "percentage_of_class": null
    },
    {
      "section": "Investments at Fair Value",
      "portfolio_company": "United States Treasury",
      "industry": "Short-Term Investments",
      "security": "Treasury Bill",
      "notes": null,
      "interest_rate": 0.0,
      "initial_acquisition_date": null,
      "maturity": null,
      "par_amount_or_quantity": 65000000,
      "cost": 64362,
      "fair_value": 64362,
      "percentage_of_class": null
    },
    {
      "section": "Investments at Fair Value",
      "portfolio_company": "MFB Northern Inst Funds Treas Portfolio Premier CL",
      "industry": "Short-Term Investments",
      "security": "Money Market",
      "notes": null,
      "interest_rate": 4.16,
      "initial_acquisition_date": null,
      "maturity": null,
      "par_amount_or_quantity": 24336133,
      "cost": 24336,
      "fair_value": 24336,
      "percentage_of_class": null
    },
    {
      "section": "Investments at Fair Value",
      "portfolio_company": "Total Short-Term Investments (63.31% of Net Assets)",
      "industry": "Total Short-Term Investments (63.31% of Net Assets)",
      "security": "Total Short-Term Investments (63.31% of Net Assets)",
      "notes": "Total Short-Term Investments (63.31% of Net Assets)",
      "interest_rate": null,
      "initial_acquisition_date": null,
      "maturity": null,
      "par_amount_or_quantity": null,
      "cost": 88698,
      "fair_value": 88698,
      "percentage_of_class": null
    },
    {
      "section": "Investments at Fair Value",
      "portfolio_company": "TOTAL INVESTMENTS (295.37% of Net Assets)",
      "industry": "TOTAL INVESTMENTS (295.37% of Net Assets)",
      "security": "TOTAL INVESTMENTS (295.37% of Net Assets)",
      "notes": 13,
      "interest_rate": null,
      "initial_acquisition_date": null,
      "maturity": null,
      "par_amount_or_quantity": null,
      "cost": "$",
      "fair_value": "$",
      "percentage_of_class": null
    },
    {
      "section": "Investments at Fair Value",
      "portfolio_company": "Other Liabilities in Excess of Net Assets (195.37% of Net Assets)",
      "industry": "Other Liabilities in Excess of Net Assets (195.37% of Net Assets)",
      "security": "Other Liabilities in Excess of Net Assets (195.37% of Net Assets)",
      "notes": "Other Liabilities in Excess of Net Assets (195.37% of Net Assets)",
      "interest_rate": null,
      "initial_acquisition_date": null,
      "maturity": null,
      "par_amount_or_quantity": null,
      "cost": null,
      "fair_value": "$",
      "percentage_of_class": null
    },
    {
      "section": "Investments at Fair Value",
      "portfolio_company": "NET ASSETS",
      "industry": "NET ASSETS",
      "security": "NET ASSETS",
      "notes": "NET ASSETS",
      "interest_rate": null,
      "initial_acquisition_date": null,
      "maturity": null,
      "par_amount_or_quantity": null,
      "cost": null,
      "fair_value": "$",
      "percentage_of_class": null
    }
  ]
}
